LICENSE.txt
README.md
setup.py
win_raw_in.egg-info/PKG-INFO
win_raw_in.egg-info/SOURCES.txt
win_raw_in.egg-info/dependency_links.txt
win_raw_in.egg-info/requires.txt
win_raw_in.egg-info/top_level.txt
winrawin/__init__.py
winrawin/_api.py
winrawin/_device_id.py
winrawin/_usb_ids.py
winrawin/_win_raw_input.py
winrawin/parse.py
winrawin/usb.ids