Metadata-Version: 2.1
Name: win-raw-in
Version: 0.2.2
Summary: Enumerate raw input devices and receive input events with device ID on Windows
Home-page: https://github.com/holl-/win-raw-in
Author: Philipp Holl
Author-email: philipp@mholl.de
License: MIT
Keywords: keyboard mouse hook raw input
Classifier: Development Status :: 4 - Beta
Classifier: License :: OSI Approved :: MIT License
Classifier: Operating System :: Microsoft :: Windows
Classifier: Programming Language :: Python :: 3
Classifier: Topic :: Software Development :: Libraries :: Python Modules
Classifier: Topic :: Utilities
License-File: LICENSE.txt
